pyps4_homeassistant/__init__.py
pyps4_homeassistant/__version__.py
pyps4_homeassistant/client.py
pyps4_homeassistant/connection.py
pyps4_homeassistant/credential.py
pyps4_homeassistant/ddp.py
pyps4_homeassistant/errors.py
pyps4_homeassistant/helpers.py
pyps4_homeassistant/media_art.py
pyps4_homeassistant/ps4.py
pyps4_homeassistant-0.8.7.2.dist-info/LICENSE
pyps4_homeassistant-0.8.7.2.dist-info/METADATA
pyps4_homeassistant-0.8.7.2.dist-info/WHEEL
pyps4_homeassistant-0.8.7.2.dist-info/top_level.txt
pyps4_homeassistant-0.8.7.2.dist-info/RECORD
