Metadata-Version: 2.1
Name: pyps4-homeassistant
Version: 0.8.7.2
Summary: PS4 2nd Screen Python Library
Home-page: https://github.com/ktnrg45/pyps4-homeassistant
Author: ktnrg45
Author-email: ktnrg45@gmail.com
License: LGPLv2+
Keywords: playstation sony ps4
Platform: UNKNOWN
Classifier: Development Status :: 3 - Alpha
Classifier: Environment :: Console
Classifier: License :: OSI Approved :: GNU Lesser General Public License v2 or later (LGPLv2+)
Classifier: Natural Language :: English
Classifier: Operating System :: OS Independent
Classifier: Programming Language :: Python :: 3.5
Classifier: Programming Language :: Python :: 3.6
Classifier: Programming Language :: Python :: 3.7
Classifier: Topic :: Software Development :: Libraries :: Python Modules
Requires-Python: >=3.5.3
Requires-Dist: aiohttp (>=3.5.4)
Requires-Dist: construct (>=2.9.45)
Requires-Dist: pycryptodomex (>=3.7.2)
